Metadata-Version: 1.0
Name: statpackagesjuyoungkim
Version: 1.0
Summary: Gaussian distributions
Home-page: UNKNOWN
Author: UNKNOWN
Author-email: UNKNOWN
License: UNKNOWN
Platform: UNKNOWN
